tests/templatetags/rankings_tests.py
tests/templatetags/__init__.py
tests/templatetags/recommendations_tests.py
django_oscar_easyrec-0.0.9.dist-info/METADATA
django_oscar_easyrec-0.0.9.dist-info/metadata.json
django_oscar_easyrec-0.0.9.dist-info/top_level.txt
django_oscar_easyrec-0.0.9.dist-info/WHEEL
django_oscar_easyrec-0.0.9.dist-info/DESCRIPTION.rst
django_oscar_easyrec-0.0.9.dist-info/RECORD
sandbox/sandbox/settings.py
sandbox/sandbox/__init__.py
sandbox/sandbox/urls.py
sandbox/sandbox/wsgi.py
easyrec/tasks.py
easyrec/gateway.py
easyrec/receivers.py
easyrec/errors.py
easyrec/models.py
easyrec/utils.py
easyrec/__init__.py
easyrec/management/__init__.py
easyrec/management/commands/easyrec-import-orders.py
easyrec/management/commands/__init__.py
easyrec/templatetags/rankings.py
easyrec/templatetags/__init__.py
easyrec/templatetags/recommendations.py
