Metadata-Version: 2.0
Name: django-oscar-easyrec
Version: 0.0.9
Summary: easyrec recommendations module for django-oscar
Home-page: https://github.com/tangentlabs/django-oscar-easyrec
Author: Jonathan Moss
Author-email: jonathan.moss@tangentsnowball.com.au
License: BSD
Keywords: Recommendation,easyrec
Platform: UNKNOWN
Classifier: Environment :: Web Environment
Classifier: Framework :: Django
Classifier: Intended Audience :: Developers
Classifier: License :: OSI Approved :: BSD License
Classifier: Operating System :: OS Independent
Classifier: Programming Language :: Python
Classifier: Programming Language :: Python :: 2
Classifier: Programming Language :: Python :: 2.6
Classifier: Programming Language :: Python :: 2.7
Requires-Dist: django-oscar (>=0.5,<0.8)
Requires-Dist: requests (>=1.1.0)
